README.rst
setup.py
cos_dumps_file_list.egg-info/PKG-INFO
cos_dumps_file_list.egg-info/SOURCES.txt
cos_dumps_file_list.egg-info/dependency_links.txt
cos_dumps_file_list.egg-info/entry_points.txt
cos_dumps_file_list.egg-info/requires.txt
cos_dumps_file_list.egg-info/top_level.txt
dump_bucket/__init__.py
dump_bucket/main.py