Metadata-Version: 1.0
Name: cos-dumps-file-list
Version: 0.0.2
Summary: simple tool that could be used to dump file list within cos bucket
Home-page: https://www.qcloud.com/
Author: liuchang
Author-email: liuchang0812@gmail.com
License: MIT
Platform: UNKNOWN
